funxuner.py
funxuner-1.7.0.dist-info/DESCRIPTION.rst
funxuner-1.7.0.dist-info/METADATA
funxuner-1.7.0.dist-info/RECORD
funxuner-1.7.0.dist-info/WHEEL
funxuner-1.7.0.dist-info/metadata.json
funxuner-1.7.0.dist-info/top_level.txt
