Metadata-Version: 2.0
Name: funxuner
Version: 1.7.0
Summary: A simple printer of nested lists ,hanyupinyin used
Home-page: http://www.sina.com
Author: Eric Chen
Author-email: chenyongyuan@sina.com
License: UNKNOWN
Platform: UNKNOWN
